demo/__init__.py
demo/settings.py
hmmerclust/__init__.py
hmmerclust/hmmerclust.py
hmmerclust-0.0.1.dev5.dist-info/DESCRIPTION.rst
hmmerclust-0.0.1.dev5.dist-info/entry_points.txt
hmmerclust-0.0.1.dev5.dist-info/METADATA
hmmerclust-0.0.1.dev5.dist-info/metadata.json
hmmerclust-0.0.1.dev5.dist-info/RECORD
hmmerclust-0.0.1.dev5.dist-info/top_level.txt
hmmerclust-0.0.1.dev5.dist-info/WHEEL
