Metadata-Version: 2.0
Name: hmmerclust
Version: 0.0.1.dev5
Summary: Detection and analysis of gene clusters in bacterial genomes.
Home-page: https://github.com/mattsolo1/hmmerclust
Author: Mathew Solomonson
Author-email: ggmatt@gmail.com
License: MIT
Keywords: bioinformatics
Platform: UNKNOWN
Classifier: Development Status :: 3 - Alpha
Classifier: Intended Audience :: Developers
Classifier: Topic :: Software Development :: Build Tools
Classifier: License :: OSI Approved :: MIT License
Classifier: Programming Language :: Python :: 2.7
Provides-Extra: dev
Requires-Dist: check-manifest; extra == 'dev'
Provides-Extra: test
Requires-Dist: coverage; extra == 'test'
